[
  {
    "letter": "T",
    "positions": [
      {
        "title": "Technik mechanik obróbki skrawaniem",
        "url": "https://wynagrodzenia.pl/moja-placa/ile-zarabia-technik-mechanik-obrobki-skrawaniem",
        "category": [
          "brak kategorii"
        ],
        "update_date": "styczeń 2025",
        "sample_size": 12,
        "related_positions": null,
        "salaries": {
          "gross": {
            "median": 4120,
            "p25": 3650,
            "p75": 7280
          },
          "net": {
            "median": 3098,
            "p25": 2798,
            "p75": 5222
          },
          "gender_distribution": {
            "women": {
              "count": 0,
              "percentage": 0
            },
            "men": {
              "count": 12,
              "percentage": 100
            }
          },
          "benefits": [
            {
              "name": "ubezpieczenie na życie/NNW",
              "percentage": 30
            },
            {
              "name": "szkolenia/kursy zawodowe",
              "percentage": 20
            },
            {
              "name": "telefon komórkowy do użytku prywatnego",
              "percentage": 10
            }
          ]
        },
        "levels": null,
        "responsibilities": null
      }
    ]
  }
]