[
  {
    "letter": "S",
    "positions": [
      {
        "title": "Specjalista ds. administracyjnych",
        "url": "https://wynagrodzenia.pl/moja-placa/ile-zarabia-specjalista-ds-administracyjnych",
        "category": [
          "administracja"
        ],
        "update_date": "styczeń 2025",
        "sample_size": 1963,
        "related_positions": [
          {
            "title": "specjalista ds. administracyjnych"
          },
          {
            "title": "specjalista ds. administracji"
          },
          {
            "title": "specjalista do spraw administracyjnych"
          },
          {
            "title": "specjalista do spraw administracji."
          }
        ],
        "salaries": null,
        "levels": [
          {
            "level": "młodszy specjalista",
            "salaries": {
              "gross": {
                "median": 5780,
                "p25": 4950,
                "p75": 6880
              },
              "net": {
                "median": 4270,
                "p25": 3704,
                "p75": 5020
              }
            },
            "gender_distribution": {
              "women": {
                "count": 242,
                "percentage": 86
              },
              "men": {
                "count": 41,
                "percentage": 14
              }
            },
            "benefits": [
              {
                "name": "karnety na siłownie i do klubów fitness",
                "percentage": 56
              },
              {
                "name": "prywatna opieka medyczna dla pracownika",
                "percentage": 47
              },
              {
                "name": "imprezy integracyjne",
                "percentage": 43
              }
            ]
          },
          {
            "level": "specjalista",
            "salaries": {
              "gross": {
                "median": 6060,
                "p25": 5240,
                "p75": 7160
              },
              "net": {
                "median": 4462,
                "p25": 3902,
                "p75": 5211
              }
            },
            "gender_distribution": {
              "women": {
                "count": 1758,
                "percentage": 90
              },
              "men": {
                "count": 205,
                "percentage": 10
              }
            },
            "benefits": [
              {
                "name": "możliwość pracy zdalnej",
                "percentage": 38
              },
              {
                "name": "prywatna opieka medyczna dla pracownika",
                "percentage": 34
              },
              {
                "name": "karnety na siłownie i do klubów fitness",
                "percentage": 33
              }
            ]
          },
          {
            "level": "starszy specjalista",
            "salaries": {
              "gross": {
                "median": 6820,
                "p25": 5770,
                "p75": 8620
              },
              "net": {
                "median": 4979,
                "p25": 4264,
                "p75": 6206
              }
            },
            "gender_distribution": {
              "women": {
                "count": 519,
                "percentage": 84
              },
              "men": {
                "count": 100,
                "percentage": 16
              }
            },
            "benefits": [
              {
                "name": "prywatna opieka medyczna dla pracownika",
                "percentage": 48
              },
              {
                "name": "możliwość pracy zdalnej",
                "percentage": 46
              },
              {
                "name": "karnety na siłownie i do klubów fitness",
                "percentage": 41
              }
            ]
          }
        ],
        "responsibilities": [
          "organizowanie sprawnej pracy biura,",
          "nadzór nad pracą podległego personelu",
          "nadzór nad zaopatrzeniem w artykuły niezbędne dla funkcjonowania biura,",
          "nadzór nad sprawami gospodarczymi, inwestycyjnymi, transportem,",
          "organizowanie pracy firm współpracujących (np. firm remontowo-budowlanych, serwisowych itp.)"
        ]
      }
    ]
  }
]