[
  {
    "letter": "K",
    "positions": [
      {
        "title": "Kierownik ds. technicznych i serwisu",
        "url": "https://wynagrodzenia.pl/moja-placa/ile-zarabia-kierownik-ds-technicznych-i-serwisu",
        "category": [
          "serwis",
          "utrzymanie ruchu"
        ],
        "update_date": "styczeń 2025",
        "sample_size": 604,
        "related_positions": [
          {
            "title": "kierownik ds. technicznych i serwisu"
          },
          {
            "title": "kierownik ds. technicznych"
          },
          {
            "title": "kierownik ds. serwisu"
          },
          {
            "title": "kierownik do spraw technicznych i serwisu"
          },
          {
            "title": "kierownik do spraw technicznych"
          },
          {
            "title": "kierownik do spraw serwisu."
          }
        ],
        "salaries": {
          "gross": {
            "median": 10220,
            "p25": 8000,
            "p75": 13910
          },
          "net": {
            "median": 7297,
            "p25": 5784,
            "p75": 9813
          },
          "gender_distribution": {
            "women": {
              "count": 74,
              "percentage": 12
            },
            "men": {
              "count": 530,
              "percentage": 88
            }
          },
          "benefits": [
            {
              "name": "możliwość pracy zdalnej",
              "percentage": 36
            },
            {
              "name": "telefon komórkowy do użytku prywatnego",
              "percentage": 36
            },
            {
              "name": "prywatna opieka medyczna dla pracownika",
              "percentage": 33
            }
          ]
        },
        "levels": null,
        "responsibilities": [
          "odpowiedzialność za utrzymanie ruchu linii i ich wysoką wydajność,",
          "planowanie i wykonywanie budżetu działu technicznego,",
          "zarządzanie sprzętem oraz zapewnienie wysokiej wydajności sprzętu,",
          "optymalne zarządzanie zapasami części zamiennych (aspekt kosztowy i czasowy),",
          "monitorowanie zużycia mediów,",
          "dbałość o zgodność przebiegu procesu produkcji z normami ochrony środowiska,",
          "kierowanie pracą podległego zespołu."
        ]
      }
    ]
  }
]