[
  {
    "letter": "K",
    "positions": [
      {
        "title": "Kierownik linii produkcyjnej",
        "url": "https://wynagrodzenia.pl/moja-placa/ile-zarabia-kierownik-linii-produkcyjnej",
        "category": [
          "produkcja",
          "przemysł"
        ],
        "update_date": "styczeń 2025",
        "sample_size": 18,
        "related_positions": null,
        "salaries": {
          "gross": {
            "median": 9900,
            "p25": 7030,
            "p75": 11090
          },
          "net": {
            "median": 7079,
            "p25": 5122,
            "p75": 7890
          },
          "gender_distribution": {
            "women": {
              "count": 4,
              "percentage": 22
            },
            "men": {
              "count": 14,
              "percentage": 78
            }
          },
          "benefits": []
        },
        "levels": null,
        "responsibilities": [
          "realizacja planów wyznaczonych dla linii produkcyjnej,",
          "nadzór nad prawidłowym przebiegiem procesów produkcyjnych,",
          "organizacja obsługi maszyn, narzędzi i urządzeń kontrolnych,",
          "nadzór nad służbami przygotowania i realizacji produkcji,",
          "kontrola zaopatrzenia w surowce,",
          "nadzorowanie organizacji stanowisk pracy i linii produkcyjnych,",
          "ciągłe kontrolowanie produkcji."
        ]
      }
    ]
  }
]