[
  {
    "letter": "I",
    "positions": [
      {
        "title": "Inżynier ds. sieci IT",
        "url": "https://wynagrodzenia.pl/moja-placa/ile-zarabia-inzynier-ds-sieci-it",
        "category": [
          "it"
        ],
        "update_date": "styczeń 2025",
        "sample_size": 134,
        "related_positions": [
          {
            "title": "inżynier ds. sieci IT"
          },
          {
            "title": "inżynier sieci IT"
          },
          {
            "title": "inżynier do spraw sieci IT."
          }
        ],
        "salaries": null,
        "levels": [
          {
            "level": "młodszy specjalista",
            "salaries": {
              "gross": {
                "median": 7160,
                "p25": 6370,
                "p75": 8480
              },
              "net": {
                "median": 5211,
                "p25": 4672,
                "p75": 6111
              }
            },
            "gender_distribution": {
              "women": {
                "count": 8,
                "percentage": 13
              },
              "men": {
                "count": 53,
                "percentage": 87
              }
            },
            "benefits": []
          },
          {
            "level": "specjalista",
            "salaries": {
              "gross": {
                "median": 11130,
                "p25": 8620,
                "p75": 14190
              },
              "net": {
                "median": 7918,
                "p25": 6206,
                "p75": 10004
              }
            },
            "gender_distribution": {
              "women": {
                "count": 9,
                "percentage": 7
              },
              "men": {
                "count": 125,
                "percentage": 93
              }
            },
            "benefits": [
              {
                "name": "możliwość pracy zdalnej",
                "percentage": 75
              },
              {
                "name": "prywatna opieka medyczna dla pracownika",
                "percentage": 50
              },
              {
                "name": "karnety na siłownie i do klubów fitness",
                "percentage": 50
              }
            ]
          },
          {
            "level": "starszy specjalista",
            "salaries": {
              "gross": {
                "median": 16340,
                "p25": 13300,
                "p75": 19610
              },
              "net": {
                "median": 11469,
                "p25": 9397,
                "p75": 13698
              }
            },
            "gender_distribution": {
              "women": {
                "count": 9,
                "percentage": 9
              },
              "men": {
                "count": 92,
                "percentage": 91
              }
            },
            "benefits": []
          }
        ],
        "responsibilities": [
          "buduje sieć LAN/WAN,",
          "rozbudowuje i modernizuje sieć,",
          "konfiguruje urządzenia transmisyjne,",
          "uruchamia oraz analizuje pracę sieci wraz z niezbędnymi pomiarami."
        ]
      }
    ]
  }
]