[
  {
    "letter": "I",
    "positions": [
      {
        "title": "Inżynier sprzedaży",
        "url": "https://wynagrodzenia.pl/moja-placa/ile-zarabia-inzynier-sprzedazy",
        "category": [
          "sprzedaż",
          "handel"
        ],
        "update_date": "styczeń 2025",
        "sample_size": 336,
        "related_positions": null,
        "salaries": null,
        "levels": [
          {
            "level": "młodszy specjalista",
            "salaries": {
              "gross": {
                "median": 8350,
                "p25": 6820,
                "p75": 10350
              },
              "net": {
                "median": 6022,
                "p25": 4979,
                "p75": 7385
              }
            },
            "gender_distribution": {
              "women": {
                "count": 15,
                "percentage": 23
              },
              "men": {
                "count": 50,
                "percentage": 77
              }
            },
            "benefits": [
              {
                "name": "samochód osobowy do użytku prywatnego",
                "percentage": 70
              },
              {
                "name": "możliwość pracy zdalnej",
                "percentage": 50
              },
              {
                "name": "telefon komórkowy do użytku prywatnego",
                "percentage": 50
              }
            ]
          },
          {
            "level": "specjalista",
            "salaries": {
              "gross": {
                "median": 9850,
                "p25": 7650,
                "p75": 13020
              },
              "net": {
                "median": 7045,
                "p25": 5545,
                "p75": 9206
              }
            },
            "gender_distribution": {
              "women": {
                "count": 75,
                "percentage": 22
              },
              "men": {
                "count": 261,
                "percentage": 78
              }
            },
            "benefits": [
              {
                "name": "telefon komórkowy do użytku prywatnego",
                "percentage": 76
              },
              {
                "name": "ubezpieczenie na życie/NNW",
                "percentage": 72
              },
              {
                "name": "samochód osobowy do użytku prywatnego",
                "percentage": 68
              }
            ]
          },
          {
            "level": "starszy specjalista",
            "salaries": {
              "gross": {
                "median": 11280,
                "p25": 9240,
                "p75": 15350
              },
              "net": {
                "median": 8019,
                "p25": 6629,
                "p75": 10793
              }
            },
            "gender_distribution": {
              "women": {
                "count": 22,
                "percentage": 13
              },
              "men": {
                "count": 145,
                "percentage": 87
              }
            },
            "benefits": [
              {
                "name": "możliwość pracy zdalnej",
                "percentage": 63
              },
              {
                "name": "prywatna opieka medyczna dla pracownika",
                "percentage": 63
              },
              {
                "name": "telefon komórkowy do użytku prywatnego",
                "percentage": 57
              }
            ]
          }
        ],
        "responsibilities": null
      }
    ]
  }
]