[
  {
    "letter": "A",
    "positions": [
      {
        "title": "Archeolog",
        "url": "https://wynagrodzenia.pl/moja-placa/ile-zarabia-archeolog",
        "category": [
          "badania i rozwój"
        ],
        "update_date": "styczeń 2025",
        "sample_size": 10,
        "related_positions": null,
        "salaries": {
          "gross": {
            "median": 3440,
            "p25": 2910,
            "p75": 4360
          },
          "net": {
            "median": 2513,
            "p25": 2139,
            "p75": 3161
          },
          "gender_distribution": {
            "women": {
              "count": 4,
              "percentage": 40
            },
            "men": {
              "count": 6,
              "percentage": 60
            }
          },
          "benefits": []
        },
        "levels": null,
        "responsibilities": null
      }
    ]
  }
]