[
  {
    "letter": "A",
    "positions": [
      {
        "title": "Asystent notariusza",
        "url": "https://wynagrodzenia.pl/moja-placa/ile-zarabia-asystent-notariusza",
        "category": [
          "usługi",
          "prawnicze"
        ],
        "update_date": "styczeń 2025",
        "sample_size": 62,
        "related_positions": null,
        "salaries": {
          "gross": {
            "median": 5710,
            "p25": 5090,
            "p75": 6900
          },
          "net": {
            "median": 4223,
            "p25": 3800,
            "p75": 5034
          },
          "gender_distribution": {
            "women": {
              "count": 52,
              "percentage": 84
            },
            "men": {
              "count": 10,
              "percentage": 16
            }
          },
          "benefits": []
        },
        "levels": null,
        "responsibilities": [
          "przygotowywanie projektów aktów notarialnych, poświadczeń i wypisów,",
          "obsługa klientów,",
          "wykonywanie prac biurowych,",
          "wspomaganie pracy kancelarii notarialnej"
        ]
      }
    ]
  }
]