[
  {
    "letter": "A",
    "positions": [
      {
        "title": "Asystent w dziale audytu",
        "url": "https://wynagrodzenia.pl/moja-placa/ile-zarabia-asystent-w-dziale-audytu",
        "category": [
          "finanse i controlling"
        ],
        "update_date": "styczeń 2025",
        "sample_size": 163,
        "related_positions": null,
        "salaries": {
          "gross": {
            "median": 7380,
            "p25": 6030,
            "p75": 8790
          },
          "net": {
            "median": 5361,
            "p25": 4441,
            "p75": 6322
          },
          "gender_distribution": {
            "women": {
              "count": 109,
              "percentage": 67
            },
            "men": {
              "count": 54,
              "percentage": 33
            }
          },
          "benefits": [
            {
              "name": "możliwość pracy zdalnej",
              "percentage": 75
            },
            {
              "name": "szkolenia/kursy zawodowe",
              "percentage": 75
            },
            {
              "name": "prywatna opieka medyczna dla pracownika",
              "percentage": 66
            }
          ]
        },
        "levels": null,
        "responsibilities": null
      }
    ]
  }
]